mpets/__init__.py
mpets/api/BaseApi.py
mpets/api/MpetsApi.py
mpets/api/__init__.py
mpets/api/api.py
mpets/api/methods/Auth.py
mpets/api/methods/Club.py
mpets/api/methods/Forum.py
mpets/api/methods/Main.py
mpets/api/methods/Profile.py
mpets/api/methods/Settings.py
mpets/api/methods/__init__.py
mpets/api/methods/parsers/__init__.py
mpets/api/methods/parsers/auth_parser.py
mpets/api/methods/parsers/club_parser.py
mpets/api/methods/parsers/forum_parser.py
mpets/logic/MpetsLogic.py
mpets/logic/__init__.py
mpets/models/BaseResponse.py
mpets/models/BooleanStatus.py
mpets/models/Error.py
mpets/models/__init__.py
mpets/models/auth/CookieStatus.py
mpets/models/auth/Cookies.py
mpets/models/auth/Login.py
mpets/models/auth/NicknameTypes.py
mpets/models/auth/Start.py
mpets/models/auth/__init__.py
mpets/models/club/Club.py
mpets/models/club/ClubBuild.py
mpets/models/club/ClubBuilds.py
mpets/models/club/ClubChat.py
mpets/models/club/ClubChatMessage.py
mpets/models/club/ClubPlayer.py
mpets/models/club/__init__.py
mpets/models/forum/EditThread.py
mpets/models/forum/Forum.py
mpets/models/forum/MessageEdit.py
mpets/models/forum/ThreadContent.py
mpets/models/forum/ThreadMessage.py
mpets/models/forum/__init__.py
mpets/models/main/TrainResponse.py
mpets/models/main/__init__.py
mpets/models/profile/Chest.py
mpets/models/profile/ChestItem.py
mpets/models/profile/ChestItemTypes.py
mpets/models/profile/Profile.py
mpets/models/profile/ViewProfile.py
mpets/models/profile/__init__.py
mpets/models/settings/NewPassword.py
mpets/models/settings/__init__.py
mpets/utils/__init__.py
mpets/utils/catch_error.py
mpets/utils/constants.py
mpets/utils/functions.py
mpets/utils/logger.py
mpets/utils/methods.py
mpets/utils/rate_limiter.py
mpets/utils/trace.py
mpets-0.9.22.dist-info/METADATA
mpets-0.9.22.dist-info/WHEEL
mpets-0.9.22.dist-info/top_level.txt
mpets-0.9.22.dist-info/RECORD
