Metadata-Version: 2.4
Name: mpets
Version: 0.9.22
Summary: API for game AmazingPets
Author-email: wilidon@bk.ru
Requires-Dist: aiohttp
Requires-Dist: BeautifulSoup4
Requires-Dist: lxml
Requires-Dist: aiohttp-socks
Requires-Dist: pydantic
Requires-Dist: python_rucaptcha
Requires-Dist: loguru
Requires-Dist: setuptools
Requires-Dist: requests
Requires-Dist: mkdocs-material
Requires-Dist: python-box[all]
Dynamic: author-email
Dynamic: requires-dist
Dynamic: summary
